BruteCodecChecker/LICENSE
BruteCodecChecker/README.MD
BruteCodecChecker/__init__.py
BruteCodecChecker/requirements.txt
BruteCodecChecker/thirdparty.json
BruteCodecChecker-0.21.dist-info/LICENSE.rst
BruteCodecChecker-0.21.dist-info/METADATA
BruteCodecChecker-0.21.dist-info/WHEEL
BruteCodecChecker-0.21.dist-info/top_level.txt
BruteCodecChecker-0.21.dist-info/RECORD
